{"_id":1528890876,"width":15,"height":10,"shelves":[{"x":1,"y":0,"sub":[{"article":{"shelfX":1,"shelfY":0,"id":3294,"name":"Athlon X4 880K-Q","desc":"","prod":""},"count":67},{"article":{"shelfX":1,"shelfY":0,"id":3114,"name":"A10-7870K-S","desc":"","prod":""},"count":72},{"article":{"shelfX":1,"shelfY":0,"id":1965,"name":"FX-8370E-N","desc":"","prod":""},"count":12},{"article":{"shelfX":1,"shelfY":0,"id":2131,"name":"FX-8300-X","desc":"","prod":""},"count":42}]},{"x":2,"y":0,"sub":[{"article":{"shelfX":2,"shelfY":0,"id":3407,"name":"Athlon X2 450-Z","desc":"","prod":""},"count":46},{"article":{"shelfX":2,"shelfY":0,"id":3279,"name":"Athlon X4 880K-B","desc":"","prod":""},"count":77},{"article":{"shelfX":2,"shelfY":0,"id":2877,"name":"A6-9550-P","desc":"","prod":""},"count":88},{"article":{"shelfX":2,"shelfY":0,"id":2511,"name":"Ryzen 5 2400G-N","desc":"","prod":""},"count":81}]},{"x":3,"y":0,"sub":[{"article":{"shelfX":3,"shelfY":0,"id":2753,"name":"Ryzen 3 1300X-V","desc":"","prod":""},"count":67},{"article":{"shelfX":3,"shelfY":0,"id":2311,"name":"Athlon 64 FX-62-V","desc":"","prod":""},"count":8},{"article":{"shelfX":3,"shelfY":0,"id":3219,"name":"A10-7700K-T","desc":"","prod":""},"count":77},{"article":{"shelfX":3,"shelfY":0,"id":2033,"name":"FX-8320E-D","desc":"","prod":""},"count":64}]},{"x":4,"y":0,"sub":[{"article":{"shelfX":4,"shelfY":0,"id":3116,"name":"A10-7870K-U","desc":"","prod":""},"count":84},{"article":{"shelfX":4,"shelfY":0,"id":2455,"name":"Athlon 64 FX-53-J","desc":"","prod":""},"count":8},{"article":{"shelfX":4,"shelfY":0,"id":2745,"name":"Ryzen 3 1300X-N","desc":"","prod":""},"count":40},{"article":{"shelfX":4,"shelfY":0,"id":3038,"name":"Athlon X4 845-U","desc":"","prod":""},"count":81}]},{"x":5,"y":0,"sub":[{"article":{"shelfX":5,"shelfY":0,"id":2760,"name":"Ryzen 3 1200-C","desc":"","prod":""},"count":50},{"article":{"shelfX":5,"shelfY":0,"id":3068,"name":"Athlon X4 835-Y","desc":"","prod":""},"count":24},{"article":{"shelfX":5,"shelfY":0,"id":2464,"name":"Athlon 64 FX-53-S","desc":"","prod":""},"count":45},{"article":{"shelfX":5,"shelfY":0,"id":1823,"name":"Ryzen Threadripper 1950X-B","desc":"","prod":""},"count":88}]},{"x":7,"y":0,"sub":[{"article":{"shelfX":7,"shelfY":0,"id":1863,"name":"Ryzen Threadripper 1920X-P","desc":"","prod":""},"count":9},{"article":{"shelfX":7,"shelfY":0,"id":2507,"name":"Ryzen 5 2400G-J","desc":"","prod":""},"count":20},{"article":{"shelfX":7,"shelfY":0,"id":2925,"name":"A6-9500E-L","desc":"","prod":""},"count":22},{"article":{"shelfX":7,"shelfY":0,"id":2955,"name":"Athlon X4 970-P","desc":"","prod":""},"count":41}]},{"x":8,"y":0,"sub":[{"article":{"shelfX":8,"shelfY":0,"id":2979,"name":"Athlon X4 950-N","desc":"","prod":""},"count":29},{"article":{"shelfX":8,"shelfY":0,"id":1894,"name":"Ryzen Threadripper 1900X-U","desc":"","prod":""},"count":84},{"article":{"shelfX":8,"shelfY":0,"id":2876,"name":"A6-9550-O","desc":"","prod":""},"count":68},{"article":{"shelfX":8,"shelfY":0,"id":1857,"name":"Ryzen Threadripper 1920X-J","desc":"","prod":""},"count":30}]},{"x":9,"y":0,"sub":[{"article":{"shelfX":9,"shelfY":0,"id":3024,"name":"Athlon X4 845-G","desc":"","prod":""},"count":84},{"article":{"shelfX":9,"shelfY":0,"id":2788,"name":"A12-9800-E","desc":"","prod":""},"count":31},{"article":{"shelfX":9,"shelfY":0,"id":2433,"name":"Athlon 64 FX-53-N","desc":"","prod":""},"count":88},{"article":{"shelfX":9,"shelfY":0,"id":2351,"name":"Athlon 64 FX-57-J","desc":"","prod":""},"count":21}]},{"x":10,"y":0,"sub":[{"article":{"shelfX":10,"shelfY":0,"id":2504,"name":"Ryzen 5 2400G-G","desc":"","prod":""},"count":21},{"article":{"shelfX":10,"shelfY":0,"id":2186,"name":"FX-6200-A","desc":"","prod":""},"count":60},{"article":{"shelfX":10,"shelfY":0,"id":2281,"name":"Athlon 64 FX-70-R","desc":"","prod":""},"count":80},{"article":{"shelfX":10,"shelfY":0,"id":2584,"name":"Ryzen 7 1700X-I","desc":"","prod":""},"count":58}]},{"x":11,"y":0,"sub":[{"article":{"shelfX":11,"shelfY":0,"id":2572,"name":"Ryzen 7 1800X-W","desc":"","prod":""},"count":67},{"article":{"shelfX":11,"shelfY":0,"id":2809,"name":"A12-9800-Z","desc":"","prod":""},"count":98},{"article":{"shelfX":11,"shelfY":0,"id":2481,"name":"Athlon 64 FX-51-J","desc":"","prod":""},"count":36},{"article":{"shelfX":11,"shelfY":0,"id":2125,"name":"FX-8300-R","desc":"","prod":""},"count":65}]},{"x":12,"y":0,"sub":[{"article":{"shelfX":12,"shelfY":0,"id":2805,"name":"A12-9800-V","desc":"","prod":""},"count":5},{"article":{"shelfX":12,"shelfY":0,"id":2162,"name":"FX-6300-C","desc":"","prod":""},"count":3},{"article":{"shelfX":12,"shelfY":0,"id":3251,"name":"A8-7670K-Z","desc":"","prod":""},"count":26},{"article":{"shelfX":12,"shelfY":0,"id":2850,"name":"A8-9600-O","desc":"","prod":""},"count":88}]},{"x":13,"y":0,"sub":[{"article":{"shelfX":13,"shelfY":0,"id":2488,"name":"Athlon 64 FX-51-Q","desc":"","prod":""},"count":55},{"article":{"shelfX":13,"shelfY":0,"id":1925,"name":"FX-9590-Z","desc":"","prod":""},"count":65},{"article":{"shelfX":13,"shelfY":0,"id":2396,"name":"Athlon 64 FX-55-C","desc":"","prod":""},"count":87},{"article":{"shelfX":13,"shelfY":0,"id":1951,"name":"FX-9370-Z","desc":"","prod":""},"count":89}]},{"x":0,"y":1,"sub":[{"article":{"shelfX":0,"shelfY":1,"id":1918,"name":"FX-9590-S","desc":"","prod":""},"count":71},{"article":{"shelfX":0,"shelfY":1,"id":3094,"name":"A10-7890K-Y","desc":"","prod":""},"count":18},{"article":{"shelfX":0,"shelfY":1,"id":2135,"name":"FX-6350-B","desc":"","prod":""},"count":56},{"article":{"shelfX":0,"shelfY":1,"id":2496,"name":"Athlon 64 FX-51-Y","desc":"","prod":""},"count":73}]},{"x":14,"y":1,"sub":[{"article":{"shelfX":14,"shelfY":1,"id":3071,"name":"A10-7890K-B","desc":"","prod":""},"count":81},{"article":{"shelfX":14,"shelfY":1,"id":2182,"name":"FX-6300-W","desc":"","prod":""},"count":11},{"article":{"shelfX":14,"shelfY":1,"id":3190,"name":"A10-7800-Q","desc":"","prod":""},"count":73},{"article":{"shelfX":14,"shelfY":1,"id":2904,"name":"A6-9500-Q","desc":"","prod":""},"count":45}]},{"x":0,"y":2,"sub":[{"article":{"shelfX":0,"shelfY":2,"id":3393,"name":"Athlon X2 450-L","desc":"","prod":""},"count":60},{"article":{"shelfX":0,"shelfY":2,"id":1949,"name":"FX-9370-X","desc":"","prod":""},"count":48},{"article":{"shelfX":0,"shelfY":2,"id":3029,"name":"Athlon X4 845-L","desc":"","prod":""},"count":96},{"article":{"shelfX":0,"shelfY":2,"id":3202,"name":"A10-7700K-C","desc":"","prod":""},"count":92}]},{"x":2,"y":2,"sub":[{"article":{"shelfX":2,"shelfY":2,"id":2276,"name":"Athlon 64 FX-70-M","desc":"","prod":""},"count":74},{"article":{"shelfX":2,"shelfY":2,"id":2654,"name":"Ryzen 5 1600-A","desc":"","prod":""},"count":88},{"article":{"shelfX":2,"shelfY":2,"id":3119,"name":"A10-7870K-X","desc":"","prod":""},"count":30},{"article":{"shelfX":2,"shelfY":2,"id":2086,"name":"FX-8310-E","desc":"","prod":""},"count":55}]},{"x":4,"y":2,"sub":[{"article":{"shelfX":4,"shelfY":2,"id":3077,"name":"A10-7890K-H","desc":"","prod":""},"count":13},{"article":{"shelfX":4,"shelfY":2,"id":2209,"name":"FX-6200-X","desc":"","prod":""},"count":69},{"article":{"shelfX":4,"shelfY":2,"id":3174,"name":"A10-7800-A","desc":"","prod":""},"count":2},{"article":{"shelfX":4,"shelfY":2,"id":2857,"name":"A8-9600-V","desc":"","prod":""},"count":35}]},{"x":6,"y":2,"sub":[{"article":{"shelfX":6,"shelfY":2,"id":2364,"name":"Athlon 64 FX-57-W","desc":"","prod":""},"count":49},{"article":{"shelfX":6,"shelfY":2,"id":2913,"name":"A6-9500-Z","desc":"","prod":""},"count":57},{"article":{"shelfX":6,"shelfY":2,"id":2458,"name":"Athlon 64 FX-53-M","desc":"","prod":""},"count":50},{"article":{"shelfX":6,"shelfY":2,"id":2645,"name":"Ryzen 5 1600X-R","desc":"","prod":""},"count":81}]},{"x":8,"y":2,"sub":[{"article":{"shelfX":8,"shelfY":2,"id":3316,"name":"Athlon X4 870K-M","desc":"","prod":""},"count":19},{"article":{"shelfX":8,"shelfY":2,"id":1864,"name":"Ryzen Threadripper 1920X-Q","desc":"","prod":""},"count":10},{"article":{"shelfX":8,"shelfY":2,"id":3146,"name":"A10-7860K-Y","desc":"","prod":""},"count":1},{"article":{"shelfX":8,"shelfY":2,"id":2973,"name":"Athlon X4 950-H","desc":"","prod":""},"count":40}]},{"x":10,"y":2,"sub":[{"article":{"shelfX":10,"shelfY":2,"id":2215,"name":"Athlon 64 FX-74-D","desc":"","prod":""},"count":45},{"article":{"shelfX":10,"shelfY":2,"id":3286,"name":"Athlon X4 880K-I","desc":"","prod":""},"count":29},{"article":{"shelfX":10,"shelfY":2,"id":2081,"name":"FX-8320-Z","desc":"","prod":""},"count":84},{"article":{"shelfX":10,"shelfY":2,"id":1862,"name":"Ryzen Threadripper 1920X-O","desc":"","prod":""},"count":22}]},{"x":11,"y":2,"sub":[{"article":{"shelfX":11,"shelfY":2,"id":2817,"name":"A10-9700-H","desc":"","prod":""},"count":47},{"article":{"shelfX":11,"shelfY":2,"id":2303,"name":"Athlon 64 FX-62-N","desc":"","prod":""},"count":15},{"article":{"shelfX":11,"shelfY":2,"id":2340,"name":"Athlon 64 FX-60-Y","desc":"","prod":""},"count":9},{"article":{"shelfX":11,"shelfY":2,"id":2253,"name":"Athlon 64 FX-72-P","desc":"","prod":""},"count":70}]},{"x":12,"y":2,"sub":[{"article":{"shelfX":12,"shelfY":2,"id":1937,"name":"FX-9370-L","desc":"","prod":""},"count":71},{"article":{"shelfX":12,"shelfY":2,"id":3402,"name":"Athlon X2 450-U","desc":"","prod":""},"count":83},{"article":{"shelfX":12,"shelfY":2,"id":1928,"name":"FX-9370-C","desc":"","prod":""},"count":12},{"article":{"shelfX":12,"shelfY":2,"id":2558,"name":"Ryzen 7 1800X-I","desc":"","prod":""},"count":2}]},{"x":14,"y":2,"sub":[{"article":{"shelfX":14,"shelfY":2,"id":3401,"name":"Athlon X2 450-T","desc":"","prod":""},"count":16},{"article":{"shelfX":14,"shelfY":2,"id":2484,"name":"Athlon 64 FX-51-M","desc":"","prod":""},"count":20},{"article":{"shelfX":14,"shelfY":2,"id":2857,"name":"A8-9600-V","desc":"","prod":""},"count":34},{"article":{"shelfX":14,"shelfY":2,"id":2717,"name":"Ryzen 5 1400-L","desc":"","prod":""},"count":32}]},{"x":0,"y":3,"sub":[{"article":{"shelfX":0,"shelfY":3,"id":2438,"name":"Athlon 64 FX-53-S","desc":"","prod":""},"count":45},{"article":{"shelfX":0,"shelfY":3,"id":2249,"name":"Athlon 64 FX-72-L","desc":"","prod":""},"count":35},{"article":{"shelfX":0,"shelfY":3,"id":2321,"name":"Athlon 64 FX-60-F","desc":"","prod":""},"count":29},{"article":{"shelfX":0,"shelfY":3,"id":2135,"name":"FX-6350-B","desc":"","prod":""},"count":69}]},{"x":2,"y":3,"sub":[{"article":{"shelfX":2,"shelfY":3,"id":2918,"name":"A6-9500E-E","desc":"","prod":""},"count":57},{"article":{"shelfX":2,"shelfY":3,"id":2382,"name":"Athlon 64 FX-55-O","desc":"","prod":""},"count":12},{"article":{"shelfX":2,"shelfY":3,"id":3238,"name":"A8-7670K-M","desc":"","prod":""},"count":52},{"article":{"shelfX":2,"shelfY":3,"id":2869,"name":"A6-9550-H","desc":"","prod":""},"count":84}]},{"x":3,"y":3,"sub":[{"article":{"shelfX":3,"shelfY":3,"id":1844,"name":"Ryzen Threadripper 1950X-W","desc":"","prod":""},"count":35},{"article":{"shelfX":3,"shelfY":3,"id":2880,"name":"A6-9550-S","desc":"","prod":""},"count":39},{"article":{"shelfX":3,"shelfY":3,"id":3253,"name":"A8-7650K-B","desc":"","prod":""},"count":58},{"article":{"shelfX":3,"shelfY":3,"id":3224,"name":"A10-7700K-Y","desc":"","prod":""},"count":10}]},{"x":4,"y":3,"sub":[{"article":{"shelfX":4,"shelfY":3,"id":2282,"name":"Athlon 64 FX-70-S","desc":"","prod":""},"count":71},{"article":{"shelfX":4,"shelfY":3,"id":3280,"name":"Athlon X4 880K-C","desc":"","prod":""},"count":84},{"article":{"shelfX":4,"shelfY":3,"id":3164,"name":"A10-7850K-Q","desc":"","prod":""},"count":15},{"article":{"shelfX":4,"shelfY":3,"id":2742,"name":"Ryzen 3 1300X-K","desc":"","prod":""},"count":100}]},{"x":5,"y":3,"sub":[{"article":{"shelfX":5,"shelfY":3,"id":2758,"name":"Ryzen 3 1200-A","desc":"","prod":""},"count":36},{"article":{"shelfX":5,"shelfY":3,"id":2452,"name":"Athlon 64 FX-53-G","desc":"","prod":""},"count":97},{"article":{"shelfX":5,"shelfY":3,"id":1871,"name":"Ryzen Threadripper 1920X-X","desc":"","prod":""},"count":82},{"article":{"shelfX":5,"shelfY":3,"id":2432,"name":"Athlon 64 FX-53-M","desc":"","prod":""},"count":37}]},{"x":6,"y":3,"sub":[{"article":{"shelfX":6,"shelfY":3,"id":2593,"name":"Ryzen 7 1700X-R","desc":"","prod":""},"count":2},{"article":{"shelfX":6,"shelfY":3,"id":1902,"name":"FX-9590-C","desc":"","prod":""},"count":10},{"article":{"shelfX":6,"shelfY":3,"id":2342,"name":"Athlon 64 FX-57-A","desc":"","prod":""},"count":76},{"article":{"shelfX":6,"shelfY":3,"id":2341,"name":"Athlon 64 FX-60-Z","desc":"","prod":""},"count":83}]},{"x":7,"y":3,"sub":[{"article":{"shelfX":7,"shelfY":3,"id":2527,"name":"Ryzen 5 2200G-D","desc":"","prod":""},"count":73},{"article":{"shelfX":7,"shelfY":3,"id":2728,"name":"Ryzen 5 1400-W","desc":"","prod":""},"count":32},{"article":{"shelfX":7,"shelfY":3,"id":1979,"name":"FX-8370-B","desc":"","prod":""},"count":79},{"article":{"shelfX":7,"shelfY":3,"id":2316,"name":"Athlon 64 FX-60-A","desc":"","prod":""},"count":56}]},{"x":8,"y":3,"sub":[{"article":{"shelfX":8,"shelfY":3,"id":3010,"name":"Athlon X4 940-S","desc":"","prod":""},"count":84},{"article":{"shelfX":8,"shelfY":3,"id":2225,"name":"Athlon 64 FX-74-N","desc":"","prod":""},"count":8},{"article":{"shelfX":8,"shelfY":3,"id":3087,"name":"A10-7890K-R","desc":"","prod":""},"count":58},{"article":{"shelfX":8,"shelfY":3,"id":2293,"name":"Athlon 64 FX-62-D","desc":"","prod":""},"count":27}]},{"x":10,"y":3,"sub":[{"article":{"shelfX":10,"shelfY":3,"id":2101,"name":"FX-8310-T","desc":"","prod":""},"count":43},{"article":{"shelfX":10,"shelfY":3,"id":2869,"name":"A6-9550-H","desc":"","prod":""},"count":8},{"article":{"shelfX":10,"shelfY":3,"id":3159,"name":"A10-7850K-L","desc":"","prod":""},"count":17},{"article":{"shelfX":10,"shelfY":3,"id":2631,"name":"Ryzen 5 1600X-D","desc":"","prod":""},"count":85}]},{"x":12,"y":3,"sub":[{"article":{"shelfX":12,"shelfY":3,"id":2789,"name":"A12-9800-F","desc":"","prod":""},"count":55},{"article":{"shelfX":12,"shelfY":3,"id":2031,"name":"FX-8320E-B","desc":"","prod":""},"count":70},{"article":{"shelfX":12,"shelfY":3,"id":2128,"name":"FX-8300-U","desc":"","prod":""},"count":95},{"article":{"shelfX":12,"shelfY":3,"id":2326,"name":"Athlon 64 FX-60-K","desc":"","prod":""},"count":2}]},{"x":14,"y":3,"sub":[{"article":{"shelfX":14,"shelfY":3,"id":2144,"name":"FX-6350-K","desc":"","prod":""},"count":8},{"article":{"shelfX":14,"shelfY":3,"id":3173,"name":"A10-7850K-Z","desc":"","prod":""},"count":76},{"article":{"shelfX":14,"shelfY":3,"id":2370,"name":"Athlon 64 FX-55-C","desc":"","prod":""},"count":93},{"article":{"shelfX":14,"shelfY":3,"id":1876,"name":"Ryzen Threadripper 1900X-C","desc":"","prod":""},"count":72}]},{"x":0,"y":4,"sub":[{"article":{"shelfX":0,"shelfY":4,"id":2936,"name":"A6-9500E-W","desc":"","prod":""},"count":39},{"article":{"shelfX":0,"shelfY":4,"id":2854,"name":"A8-9600-S","desc":"","prod":""},"count":26},{"article":{"shelfX":0,"shelfY":4,"id":2509,"name":"Ryzen 5 2400G-L","desc":"","prod":""},"count":19},{"article":{"shelfX":0,"shelfY":4,"id":2579,"name":"Ryzen 7 1700X-D","desc":"","prod":""},"count":87}]},{"x":10,"y":4,"sub":[{"article":{"shelfX":10,"shelfY":4,"id":1946,"name":"FX-9370-U","desc":"","prod":""},"count":27},{"article":{"shelfX":10,"shelfY":4,"id":3423,"name":"Sempron 3850-P","desc":"","prod":""},"count":80},{"article":{"shelfX":10,"shelfY":4,"id":2974,"name":"Athlon X4 950-I","desc":"","prod":""},"count":19},{"article":{"shelfX":10,"shelfY":4,"id":2878,"name":"A6-9550-Q","desc":"","prod":""},"count":90}]},{"x":12,"y":4,"sub":[{"article":{"shelfX":12,"shelfY":4,"id":2882,"name":"A6-9550-U","desc":"","prod":""},"count":6},{"article":{"shelfX":12,"shelfY":4,"id":2047,"name":"FX-8320E-R","desc":"","prod":""},"count":87},{"article":{"shelfX":12,"shelfY":4,"id":2576,"name":"Ryzen 7 1700X-A","desc":"","prod":""},"count":83},{"article":{"shelfX":12,"shelfY":4,"id":2602,"name":"Ryzen 7 1700-A","desc":"","prod":""},"count":98}]},{"x":2,"y":5,"sub":[{"article":{"shelfX":2,"shelfY":5,"id":2024,"name":"FX-8350-U","desc":"","prod":""},"count":46},{"article":{"shelfX":2,"shelfY":5,"id":3066,"name":"Athlon X4 835-W","desc":"","prod":""},"count":43},{"article":{"shelfX":2,"shelfY":5,"id":2704,"name":"Ryzen 5 1500X-Y","desc":"","prod":""},"count":38},{"article":{"shelfX":2,"shelfY":5,"id":2249,"name":"Athlon 64 FX-72-L","desc":"","prod":""},"count":69}]},{"x":3,"y":5,"sub":[{"article":{"shelfX":3,"shelfY":5,"id":3094,"name":"A10-7890K-Y","desc":"","prod":""},"count":24},{"article":{"shelfX":3,"shelfY":5,"id":2086,"name":"FX-8310-E","desc":"","prod":""},"count":9},{"article":{"shelfX":3,"shelfY":5,"id":3139,"name":"A10-7860K-R","desc":"","prod":""},"count":86},{"article":{"shelfX":3,"shelfY":5,"id":2831,"name":"A10-9700-V","desc":"","prod":""},"count":40}]},{"x":4,"y":5,"sub":[{"article":{"shelfX":4,"shelfY":5,"id":2990,"name":"Athlon X4 950-Y","desc":"","prod":""},"count":31},{"article":{"shelfX":4,"shelfY":5,"id":2542,"name":"Ryzen 5 2200G-S","desc":"","prod":""},"count":22},{"article":{"shelfX":4,"shelfY":5,"id":2351,"name":"Athlon 64 FX-57-J","desc":"","prod":""},"count":36},{"article":{"shelfX":4,"shelfY":5,"id":3106,"name":"A10-7870K-K","desc":"","prod":""},"count":64}]},{"x":5,"y":5,"sub":[{"article":{"shelfX":5,"shelfY":5,"id":2112,"name":"FX-8300-E","desc":"","prod":""},"count":64},{"article":{"shelfX":5,"shelfY":5,"id":2023,"name":"FX-8350-T","desc":"","prod":""},"count":38},{"article":{"shelfX":5,"shelfY":5,"id":2901,"name":"A6-9500-N","desc":"","prod":""},"count":9},{"article":{"shelfX":5,"shelfY":5,"id":2338,"name":"Athlon 64 FX-60-W","desc":"","prod":""},"count":83}]},{"x":6,"y":5,"sub":[{"article":{"shelfX":6,"shelfY":5,"id":3072,"name":"A10-7890K-C","desc":"","prod":""},"count":86},{"article":{"shelfX":6,"shelfY":5,"id":1844,"name":"Ryzen Threadripper 1950X-W","desc":"","prod":""},"count":86},{"article":{"shelfX":6,"shelfY":5,"id":2385,"name":"Athlon 64 FX-55-R","desc":"","prod":""},"count":80},{"article":{"shelfX":6,"shelfY":5,"id":3060,"name":"Athlon X4 835-Q","desc":"","prod":""},"count":2}]},{"x":8,"y":5,"sub":[{"article":{"shelfX":8,"shelfY":5,"id":2141,"name":"FX-6350-H","desc":"","prod":""},"count":64},{"article":{"shelfX":8,"shelfY":5,"id":2835,"name":"A10-9700-Z","desc":"","prod":""},"count":63},{"article":{"shelfX":8,"shelfY":5,"id":2609,"name":"Ryzen 7 1700-H","desc":"","prod":""},"count":93},{"article":{"shelfX":8,"shelfY":5,"id":2274,"name":"Athlon 64 FX-70-K","desc":"","prod":""},"count":38}]},{"x":14,"y":5,"sub":[{"article":{"shelfX":14,"shelfY":5,"id":2091,"name":"FX-8310-J","desc":"","prod":""},"count":37},{"article":{"shelfX":14,"shelfY":5,"id":2624,"name":"Ryzen 7 1700-W","desc":"","prod":""},"count":6},{"article":{"shelfX":14,"shelfY":5,"id":2804,"name":"A12-9800-U","desc":"","prod":""},"count":78},{"article":{"shelfX":14,"shelfY":5,"id":2601,"name":"Ryzen 7 1700X-Z","desc":"","prod":""},"count":41}]},{"x":0,"y":6,"sub":[{"article":{"shelfX":0,"shelfY":6,"id":1837,"name":"Ryzen Threadripper 1950X-P","desc":"","prod":""},"count":33},{"article":{"shelfX":0,"shelfY":6,"id":1992,"name":"FX-8370-O","desc":"","prod":""},"count":15},{"article":{"shelfX":0,"shelfY":6,"id":2517,"name":"Ryzen 5 2400G-T","desc":"","prod":""},"count":27},{"article":{"shelfX":0,"shelfY":6,"id":2715,"name":"Ryzen 5 1400-J","desc":"","prod":""},"count":91}]},{"x":2,"y":6,"sub":[{"article":{"shelfX":2,"shelfY":6,"id":1949,"name":"FX-9370-X","desc":"","prod":""},"count":49},{"article":{"shelfX":2,"shelfY":6,"id":2214,"name":"Athlon 64 FX-74-C","desc":"","prod":""},"count":54},{"article":{"shelfX":2,"shelfY":6,"id":3168,"name":"A10-7850K-U","desc":"","prod":""},"count":97},{"article":{"shelfX":2,"shelfY":6,"id":3097,"name":"A10-7870K-B","desc":"","prod":""},"count":9}]},{"x":4,"y":6,"sub":[{"article":{"shelfX":4,"shelfY":6,"id":3007,"name":"Athlon X4 940-P","desc":"","prod":""},"count":24},{"article":{"shelfX":4,"shelfY":6,"id":2919,"name":"A6-9500E-F","desc":"","prod":""},"count":13},{"article":{"shelfX":4,"shelfY":6,"id":3021,"name":"Athlon X4 845-D","desc":"","prod":""},"count":19},{"article":{"shelfX":4,"shelfY":6,"id":2963,"name":"Athlon X4 970-X","desc":"","prod":""},"count":97}]},{"x":6,"y":6,"sub":[{"article":{"shelfX":6,"shelfY":6,"id":3362,"name":"Athlon X4 840-G","desc":"","prod":""},"count":56},{"article":{"shelfX":6,"shelfY":6,"id":3021,"name":"Athlon X4 845-D","desc":"","prod":""},"count":92},{"article":{"shelfX":6,"shelfY":6,"id":2115,"name":"FX-8300-H","desc":"","prod":""},"count":43},{"article":{"shelfX":6,"shelfY":6,"id":2898,"name":"A6-9500-K","desc":"","prod":""},"count":53}]},{"x":8,"y":6,"sub":[{"article":{"shelfX":8,"shelfY":6,"id":2335,"name":"Athlon 64 FX-60-T","desc":"","prod":""},"count":84},{"article":{"shelfX":8,"shelfY":6,"id":2441,"name":"Athlon 64 FX-53-V","desc":"","prod":""},"count":61},{"article":{"shelfX":8,"shelfY":6,"id":2985,"name":"Athlon X4 950-T","desc":"","prod":""},"count":51},{"article":{"shelfX":8,"shelfY":6,"id":2756,"name":"Ryzen 3 1300X-Y","desc":"","prod":""},"count":71}]},{"x":9,"y":6,"sub":[{"article":{"shelfX":9,"shelfY":6,"id":1983,"name":"FX-8370-F","desc":"","prod":""},"count":87},{"article":{"shelfX":9,"shelfY":6,"id":2682,"name":"Ryzen 5 1500X-C","desc":"","prod":""},"count":73},{"article":{"shelfX":9,"shelfY":6,"id":3075,"name":"A10-7890K-F","desc":"","prod":""},"count":29},{"article":{"shelfX":9,"shelfY":6,"id":2555,"name":"Ryzen 7 1800X-F","desc":"","prod":""},"count":51}]},{"x":10,"y":6,"sub":[{"article":{"shelfX":10,"shelfY":6,"id":3156,"name":"A10-7850K-I","desc":"","prod":""},"count":63},{"article":{"shelfX":10,"shelfY":6,"id":3175,"name":"A10-7800-B","desc":"","prod":""},"count":55},{"article":{"shelfX":10,"shelfY":6,"id":2762,"name":"Ryzen 3 1200-E","desc":"","prod":""},"count":14},{"article":{"shelfX":10,"shelfY":6,"id":2913,"name":"A6-9500-Z","desc":"","prod":""},"count":72}]},{"x":11,"y":6,"sub":[{"article":{"shelfX":11,"shelfY":6,"id":3065,"name":"Athlon X4 835-V","desc":"","prod":""},"count":83},{"article":{"shelfX":11,"shelfY":6,"id":3202,"name":"A10-7700K-C","desc":"","prod":""},"count":33},{"article":{"shelfX":11,"shelfY":6,"id":2629,"name":"Ryzen 5 1600X-B","desc":"","prod":""},"count":35},{"article":{"shelfX":11,"shelfY":6,"id":3384,"name":"Athlon X2 450-C","desc":"","prod":""},"count":5}]},{"x":12,"y":6,"sub":[{"article":{"shelfX":12,"shelfY":6,"id":2299,"name":"Athlon 64 FX-62-J","desc":"","prod":""},"count":59},{"article":{"shelfX":12,"shelfY":6,"id":2592,"name":"Ryzen 7 1700X-Q","desc":"","prod":""},"count":81},{"article":{"shelfX":12,"shelfY":6,"id":3306,"name":"Athlon X4 870K-C","desc":"","prod":""},"count":77},{"article":{"shelfX":12,"shelfY":6,"id":3251,"name":"A8-7670K-Z","desc":"","prod":""},"count":74}]},{"x":14,"y":6,"sub":[{"article":{"shelfX":14,"shelfY":6,"id":2208,"name":"FX-6200-W","desc":"","prod":""},"count":90},{"article":{"shelfX":14,"shelfY":6,"id":2783,"name":"Ryzen 3 1200-Z","desc":"","prod":""},"count":11},{"article":{"shelfX":14,"shelfY":6,"id":2388,"name":"Athlon 64 FX-55-U","desc":"","prod":""},"count":17},{"article":{"shelfX":14,"shelfY":6,"id":3389,"name":"Athlon X2 450-H","desc":"","prod":""},"count":70}]},{"x":0,"y":7,"sub":[{"article":{"shelfX":0,"shelfY":7,"id":2431,"name":"Athlon 64 FX-53-L","desc":"","prod":""},"count":57},{"article":{"shelfX":0,"shelfY":7,"id":2770,"name":"Ryzen 3 1200-M","desc":"","prod":""},"count":76},{"article":{"shelfX":0,"shelfY":7,"id":2721,"name":"Ryzen 5 1400-P","desc":"","prod":""},"count":29},{"article":{"shelfX":0,"shelfY":7,"id":2801,"name":"A12-9800-R","desc":"","prod":""},"count":73}]},{"x":2,"y":7,"sub":[{"article":{"shelfX":2,"shelfY":7,"id":1912,"name":"FX-9590-M","desc":"","prod":""},"count":8},{"article":{"shelfX":2,"shelfY":7,"id":2046,"name":"FX-8320E-Q","desc":"","prod":""},"count":32},{"article":{"shelfX":2,"shelfY":7,"id":2015,"name":"FX-8350-L","desc":"","prod":""},"count":17},{"article":{"shelfX":2,"shelfY":7,"id":3263,"name":"A8-7650K-L","desc":"","prod":""},"count":95}]},{"x":6,"y":7,"sub":[{"article":{"shelfX":6,"shelfY":7,"id":3414,"name":"Sempron 3850-G","desc":"","prod":""},"count":77},{"article":{"shelfX":6,"shelfY":7,"id":3406,"name":"Athlon X2 450-Y","desc":"","prod":""},"count":81},{"article":{"shelfX":6,"shelfY":7,"id":3205,"name":"A10-7700K-F","desc":"","prod":""},"count":54},{"article":{"shelfX":6,"shelfY":7,"id":2508,"name":"Ryzen 5 2400G-K","desc":"","prod":""},"count":70}]},{"x":8,"y":7,"sub":[{"article":{"shelfX":8,"shelfY":7,"id":3354,"name":"Athlon X4 860K-Y","desc":"","prod":""},"count":21},{"article":{"shelfX":8,"shelfY":7,"id":2121,"name":"FX-8300-N","desc":"","prod":""},"count":29},{"article":{"shelfX":8,"shelfY":7,"id":1859,"name":"Ryzen Threadripper 1920X-L","desc":"","prod":""},"count":28},{"article":{"shelfX":8,"shelfY":7,"id":3284,"name":"Athlon X4 880K-G","desc":"","prod":""},"count":30}]},{"x":10,"y":7,"sub":[{"article":{"shelfX":10,"shelfY":7,"id":2254,"name":"Athlon 64 FX-72-Q","desc":"","prod":""},"count":35},{"article":{"shelfX":10,"shelfY":7,"id":2520,"name":"Ryzen 5 2400G-W","desc":"","prod":""},"count":31},{"article":{"shelfX":10,"shelfY":7,"id":1957,"name":"FX-8370E-F","desc":"","prod":""},"count":73},{"article":{"shelfX":10,"shelfY":7,"id":3116,"name":"A10-7870K-U","desc":"","prod":""},"count":33}]},{"x":12,"y":7,"sub":[{"article":{"shelfX":12,"shelfY":7,"id":2397,"name":"Athlon 64 FX-55-D","desc":"","prod":""},"count":93},{"article":{"shelfX":12,"shelfY":7,"id":1952,"name":"FX-8370E-A","desc":"","prod":""},"count":62},{"article":{"shelfX":12,"shelfY":7,"id":3020,"name":"Athlon X4 845-C","desc":"","prod":""},"count":53},{"article":{"shelfX":12,"shelfY":7,"id":2344,"name":"Athlon 64 FX-57-C","desc":"","prod":""},"count":21}]},{"x":14,"y":7,"sub":[{"article":{"shelfX":14,"shelfY":7,"id":2611,"name":"Ryzen 7 1700-J","desc":"","prod":""},"count":88},{"article":{"shelfX":14,"shelfY":7,"id":1981,"name":"FX-8370-D","desc":"","prod":""},"count":30},{"article":{"shelfX":14,"shelfY":7,"id":2265,"name":"Athlon 64 FX-70-B","desc":"","prod":""},"count":51},{"article":{"shelfX":14,"shelfY":7,"id":2616,"name":"Ryzen 7 1700-O","desc":"","prod":""},"count":7}]},{"x":0,"y":8,"sub":[{"article":{"shelfX":0,"shelfY":8,"id":2112,"name":"FX-8300-E","desc":"","prod":""},"count":21},{"article":{"shelfX":0,"shelfY":8,"id":3204,"name":"A10-7700K-E","desc":"","prod":""},"count":46},{"article":{"shelfX":0,"shelfY":8,"id":2300,"name":"Athlon 64 FX-62-K","desc":"","prod":""},"count":40},{"article":{"shelfX":0,"shelfY":8,"id":2061,"name":"FX-8320-F","desc":"","prod":""},"count":18}]},{"x":14,"y":8,"sub":[{"article":{"shelfX":14,"shelfY":8,"id":1853,"name":"Ryzen Threadripper 1920X-F","desc":"","prod":""},"count":5},{"article":{"shelfX":14,"shelfY":8,"id":2233,"name":"Athlon 64 FX-74-V","desc":"","prod":""},"count":10},{"article":{"shelfX":14,"shelfY":8,"id":2659,"name":"Ryzen 5 1600-F","desc":"","prod":""},"count":22},{"article":{"shelfX":14,"shelfY":8,"id":2281,"name":"Athlon 64 FX-70-R","desc":"","prod":""},"count":87}]},{"x":1,"y":9,"sub":[{"article":{"shelfX":1,"shelfY":9,"id":2691,"name":"Ryzen 5 1500X-L","desc":"","prod":""},"count":80},{"article":{"shelfX":1,"shelfY":9,"id":2265,"name":"Athlon 64 FX-70-B","desc":"","prod":""},"count":96},{"article":{"shelfX":1,"shelfY":9,"id":2728,"name":"Ryzen 5 1400-W","desc":"","prod":""},"count":60},{"article":{"shelfX":1,"shelfY":9,"id":2001,"name":"FX-8370-X","desc":"","prod":""},"count":93}]},{"x":2,"y":9,"sub":[{"article":{"shelfX":2,"shelfY":9,"id":2591,"name":"Ryzen 7 1700X-P","desc":"","prod":""},"count":70},{"article":{"shelfX":2,"shelfY":9,"id":2292,"name":"Athlon 64 FX-62-C","desc":"","prod":""},"count":62},{"article":{"shelfX":2,"shelfY":9,"id":3169,"name":"A10-7850K-V","desc":"","prod":""},"count":51},{"article":{"shelfX":2,"shelfY":9,"id":1943,"name":"FX-9370-R","desc":"","prod":""},"count":38}]},{"x":3,"y":9,"sub":[{"article":{"shelfX":3,"shelfY":9,"id":1889,"name":"Ryzen Threadripper 1900X-P","desc":"","prod":""},"count":83},{"article":{"shelfX":3,"shelfY":9,"id":2553,"name":"Ryzen 7 1800X-D","desc":"","prod":""},"count":8},{"article":{"shelfX":3,"shelfY":9,"id":2420,"name":"Athlon 64 FX-53-A","desc":"","prod":""},"count":8},{"article":{"shelfX":3,"shelfY":9,"id":2779,"name":"Ryzen 3 1200-V","desc":"","prod":""},"count":1}]},{"x":4,"y":9,"sub":[{"article":{"shelfX":4,"shelfY":9,"id":1826,"name":"Ryzen Threadripper 1950X-E","desc":"","prod":""},"count":94},{"article":{"shelfX":4,"shelfY":9,"id":2455,"name":"Athlon 64 FX-53-J","desc":"","prod":""},"count":11},{"article":{"shelfX":4,"shelfY":9,"id":2767,"name":"Ryzen 3 1200-J","desc":"","prod":""},"count":40},{"article":{"shelfX":4,"shelfY":9,"id":1920,"name":"FX-9590-U","desc":"","prod":""},"count":15}]},{"x":5,"y":9,"sub":[{"article":{"shelfX":5,"shelfY":9,"id":2356,"name":"Athlon 64 FX-57-O","desc":"","prod":""},"count":57},{"article":{"shelfX":5,"shelfY":9,"id":2463,"name":"Athlon 64 FX-53-R","desc":"","prod":""},"count":16},{"article":{"shelfX":5,"shelfY":9,"id":3279,"name":"Athlon X4 880K-B","desc":"","prod":""},"count":75},{"article":{"shelfX":5,"shelfY":9,"id":2681,"name":"Ryzen 5 1500X-B","desc":"","prod":""},"count":52}]},{"x":6,"y":9,"sub":[{"article":{"shelfX":6,"shelfY":9,"id":3094,"name":"A10-7890K-Y","desc":"","prod":""},"count":99},{"article":{"shelfX":6,"shelfY":9,"id":2444,"name":"Athlon 64 FX-53-Y","desc":"","prod":""},"count":59},{"article":{"shelfX":6,"shelfY":9,"id":2225,"name":"Athlon 64 FX-74-N","desc":"","prod":""},"count":19},{"article":{"shelfX":6,"shelfY":9,"id":2362,"name":"Athlon 64 FX-57-U","desc":"","prod":""},"count":91}]},{"x":7,"y":9,"sub":[{"article":{"shelfX":7,"shelfY":9,"id":1827,"name":"Ryzen Threadripper 1950X-F","desc":"","prod":""},"count":81},{"article":{"shelfX":7,"shelfY":9,"id":2126,"name":"FX-8300-S","desc":"","prod":""},"count":23},{"article":{"shelfX":7,"shelfY":9,"id":3265,"name":"A8-7650K-N","desc":"","prod":""},"count":49},{"article":{"shelfX":7,"shelfY":9,"id":2032,"name":"FX-8320E-C","desc":"","prod":""},"count":71}]},{"x":8,"y":9,"sub":[{"article":{"shelfX":8,"shelfY":9,"id":2652,"name":"Ryzen 5 1600X-Y","desc":"","prod":""},"count":93},{"article":{"shelfX":8,"shelfY":9,"id":2822,"name":"A10-9700-M","desc":"","prod":""},"count":69},{"article":{"shelfX":8,"shelfY":9,"id":2697,"name":"Ryzen 5 1500X-R","desc":"","prod":""},"count":57},{"article":{"shelfX":8,"shelfY":9,"id":2963,"name":"Athlon X4 970-X","desc":"","prod":""},"count":40}]},{"x":10,"y":9,"sub":[{"article":{"shelfX":10,"shelfY":9,"id":3029,"name":"Athlon X4 845-L","desc":"","prod":""},"count":24},{"article":{"shelfX":10,"shelfY":9,"id":3019,"name":"Athlon X4 845-B","desc":"","prod":""},"count":98},{"article":{"shelfX":10,"shelfY":9,"id":2936,"name":"A6-9500E-W","desc":"","prod":""},"count":89},{"article":{"shelfX":10,"shelfY":9,"id":1867,"name":"Ryzen Threadripper 1920X-T","desc":"","prod":""},"count":70}]},{"x":11,"y":9,"sub":[{"article":{"shelfX":11,"shelfY":9,"id":1958,"name":"FX-8370E-G","desc":"","prod":""},"count":93},{"article":{"shelfX":11,"shelfY":9,"id":3343,"name":"Athlon X4 860K-N","desc":"","prod":""},"count":89},{"article":{"shelfX":11,"shelfY":9,"id":3363,"name":"Athlon X4 840-H","desc":"","prod":""},"count":52},{"article":{"shelfX":11,"shelfY":9,"id":2153,"name":"FX-6350-T","desc":"","prod":""},"count":72}]},{"x":12,"y":9,"sub":[{"article":{"shelfX":12,"shelfY":9,"id":2306,"name":"Athlon 64 FX-62-Q","desc":"","prod":""},"count":53},{"article":{"shelfX":12,"shelfY":9,"id":3371,"name":"Athlon X4 840-P","desc":"","prod":""},"count":47},{"article":{"shelfX":12,"shelfY":9,"id":3323,"name":"Athlon X4 870K-T","desc":"","prod":""},"count":11},{"article":{"shelfX":12,"shelfY":9,"id":2962,"name":"Athlon X4 970-W","desc":"","prod":""},"count":38}]},{"x":13,"y":9,"sub":[{"article":{"shelfX":13,"shelfY":9,"id":1860,"name":"Ryzen Threadripper 1920X-M","desc":"","prod":""},"count":35},{"article":{"shelfX":13,"shelfY":9,"id":2861,"name":"A8-9600-Z","desc":"","prod":""},"count":90},{"article":{"shelfX":13,"shelfY":9,"id":2105,"name":"FX-8310-X","desc":"","prod":""},"count":51},{"article":{"shelfX":13,"shelfY":9,"id":2416,"name":"Athlon 64 FX-55-W","desc":"","prod":""},"count":47}]}],"entrances":[{"x":6,"y":0},{"x":14,"y":4},{"x":0,"y":5},{"x":9,"y":9}]}